[
  {
    "surah_number": 90,
    "surah_name_arabic": "البلد",
    "surah_name_english": "Al-Balad",
    "ayah_number": 1,
    "tafsir_author": "Ibn Katheer",
    "url": "https://tafsir.app/ibn-katheer/90/1",
    "extraction_timestamp": "2025-06-30 13:05:22"
  },
  {
    "surah_number": 90,
    "surah_name_arabic": "البلد",
    "surah_name_english": "Al-Balad",
    "ayah_number": 2,
    "tafsir_author": "Ibn Katheer",
    "url": "https://tafsir.app/ibn-katheer/90/2",
    "extraction_timestamp": "2025-06-30 13:05:23"
  },
  {
    "surah_number": 90,
    "surah_name_arabic": "البلد",
    "surah_name_english": "Al-Balad",
    "ayah_number": 3,
    "tafsir_author": "Ibn Katheer",
    "url": "https://tafsir.app/ibn-katheer/90/3",
    "extraction_timestamp": "2025-06-30 13:05:25"
  },
  {
    "surah_number": 90,
    "surah_name_arabic": "البلد",
    "surah_name_english": "Al-Balad",
    "ayah_number": 4,
    "tafsir_author": "Ibn Katheer",
    "url": "https://tafsir.app/ibn-katheer/90/4",
    "extraction_timestamp": "2025-06-30 13:05:27"
  },
  {
    "surah_number": 90,
    "surah_name_arabic": "البلد",
    "surah_name_english": "Al-Balad",
    "ayah_number": 5,
    "tafsir_author": "Ibn Katheer",
    "url": "https://tafsir.app/ibn-katheer/90/5",
    "extraction_timestamp": "2025-06-30 13:05:29"
  },
  {
    "surah_number": 90,
    "surah_name_arabic": "البلد",
    "surah_name_english": "Al-Balad",
    "ayah_number": 6,
    "tafsir_author": "Ibn Katheer",
    "url": "https://tafsir.app/ibn-katheer/90/6",
    "extraction_timestamp": "2025-06-30 13:05:30"
  },
  {
    "surah_number": 90,
    "surah_name_arabic": "البلد",
    "surah_name_english": "Al-Balad",
    "ayah_number": 7,
    "tafsir_author": "Ibn Katheer",
    "url": "https://tafsir.app/ibn-katheer/90/7",
    "extraction_timestamp": "2025-06-30 13:05:32"
  },
  {
    "surah_number": 90,
    "surah_name_arabic": "البلد",
    "surah_name_english": "Al-Balad",
    "ayah_number": 8,
    "tafsir_author": "Ibn Katheer",
    "url": "https://tafsir.app/ibn-katheer/90/8",
    "extraction_timestamp": "2025-06-30 13:05:34"
  },
  {
    "surah_number": 90,
    "surah_name_arabic": "البلد",
    "surah_name_english": "Al-Balad",
    "ayah_number": 9,
    "tafsir_author": "Ibn Katheer",
    "url": "https://tafsir.app/ibn-katheer/90/9",
    "extraction_timestamp": "2025-06-30 13:05:35"
  },
  {
    "surah_number": 90,
    "surah_name_arabic": "البلد",
    "surah_name_english": "Al-Balad",
    "ayah_number": 10,
    "tafsir_author": "Ibn Katheer",
    "url": "https://tafsir.app/ibn-katheer/90/10",
    "extraction_timestamp": "2025-06-30 13:05:37"
  },
  {
    "surah_number": 90,
    "surah_name_arabic": "البلد",
    "surah_name_english": "Al-Balad",
    "ayah_number": 11,
    "tafsir_author": "Ibn Katheer",
    "url": "https://tafsir.app/ibn-katheer/90/11",
    "extraction_timestamp": "2025-06-30 13:05:39"
  },
  {
    "surah_number": 90,
    "surah_name_arabic": "البلد",
    "surah_name_english": "Al-Balad",
    "ayah_number": 12,
    "tafsir_author": "Ibn Katheer",
    "url": "https://tafsir.app/ibn-katheer/90/12",
    "extraction_timestamp": "2025-06-30 13:05:40"
  },
  {
    "surah_number": 90,
    "surah_name_arabic": "البلد",
    "surah_name_english": "Al-Balad",
    "ayah_number": 13,
    "tafsir_author": "Ibn Katheer",
    "url": "https://tafsir.app/ibn-katheer/90/13",
    "extraction_timestamp": "2025-06-30 13:05:42"
  },
  {
    "surah_number": 90,
    "surah_name_arabic": "البلد",
    "surah_name_english": "Al-Balad",
    "ayah_number": 14,
    "tafsir_author": "Ibn Katheer",
    "url": "https://tafsir.app/ibn-katheer/90/14",
    "extraction_timestamp": "2025-06-30 13:05:44"
  },
  {
    "surah_number": 90,
    "surah_name_arabic": "البلد",
    "surah_name_english": "Al-Balad",
    "ayah_number": 15,
    "tafsir_author": "Ibn Katheer",
    "url": "https://tafsir.app/ibn-katheer/90/15",
    "extraction_timestamp": "2025-06-30 13:05:45"
  },
  {
    "surah_number": 90,
    "surah_name_arabic": "البلد",
    "surah_name_english": "Al-Balad",
    "ayah_number": 16,
    "tafsir_author": "Ibn Katheer",
    "url": "https://tafsir.app/ibn-katheer/90/16",
    "extraction_timestamp": "2025-06-30 13:05:47"
  },
  {
    "surah_number": 90,
    "surah_name_arabic": "البلد",
    "surah_name_english": "Al-Balad",
    "ayah_number": 17,
    "tafsir_author": "Ibn Katheer",
    "url": "https://tafsir.app/ibn-katheer/90/17",
    "extraction_timestamp": "2025-06-30 13:05:49"
  },
  {
    "surah_number": 90,
    "surah_name_arabic": "البلد",
    "surah_name_english": "Al-Balad",
    "ayah_number": 18,
    "tafsir_author": "Ibn Katheer",
    "url": "https://tafsir.app/ibn-katheer/90/18",
    "extraction_timestamp": "2025-06-30 13:05:50"
  },
  {
    "surah_number": 90,
    "surah_name_arabic": "البلد",
    "surah_name_english": "Al-Balad",
    "ayah_number": 19,
    "tafsir_author": "Ibn Katheer",
    "url": "https://tafsir.app/ibn-katheer/90/19",
    "extraction_timestamp": "2025-06-30 13:05:52"
  },
  {
    "surah_number": 90,
    "surah_name_arabic": "البلد",
    "surah_name_english": "Al-Balad",
    "ayah_number": 20,
    "tafsir_author": "Ibn Katheer",
    "url": "https://tafsir.app/ibn-katheer/90/20",
    "extraction_timestamp": "2025-06-30 13:05:54"
  }
]