[
  {
    "surah_number": 109,
    "surah_name_arabic": "الكافرون",
    "surah_name_english": "Al-Kafirun",
    "ayah_number": 1,
    "tafsir_author": "Al-Qurtubi",
    "url": "https://tafsir.app/qurtubi/109/1",
    "extraction_timestamp": "2025-06-25 15:39:48"
  },
  {
    "surah_number": 109,
    "surah_name_arabic": "الكافرون",
    "surah_name_english": "Al-Kafirun",
    "ayah_number": 2,
    "tafsir_author": "Al-Qurtubi",
    "url": "https://tafsir.app/qurtubi/109/2",
    "extraction_timestamp": "2025-06-25 15:39:49"
  },
  {
    "surah_number": 109,
    "surah_name_arabic": "الكافرون",
    "surah_name_english": "Al-Kafirun",
    "ayah_number": 3,
    "tafsir_author": "Al-Qurtubi",
    "url": "https://tafsir.app/qurtubi/109/3",
    "extraction_timestamp": "2025-06-25 15:39:51"
  },
  {
    "surah_number": 109,
    "surah_name_arabic": "الكافرون",
    "surah_name_english": "Al-Kafirun",
    "ayah_number": 4,
    "tafsir_author": "Al-Qurtubi",
    "url": "https://tafsir.app/qurtubi/109/4",
    "extraction_timestamp": "2025-06-25 15:39:52"
  },
  {
    "surah_number": 109,
    "surah_name_arabic": "الكافرون",
    "surah_name_english": "Al-Kafirun",
    "ayah_number": 5,
    "tafsir_author": "Al-Qurtubi",
    "url": "https://tafsir.app/qurtubi/109/5",
    "extraction_timestamp": "2025-06-25 15:39:54"
  },
  {
    "surah_number": 109,
    "surah_name_arabic": "الكافرون",
    "surah_name_english": "Al-Kafirun",
    "ayah_number": 6,
    "tafsir_author": "Al-Qurtubi",
    "url": "https://tafsir.app/qurtubi/109/6",
    "extraction_timestamp": "2025-06-25 15:39:55"
  }
]